setup.py
binomial_probability/Binomialdistribution.py
binomial_probability/Gaussiandistribution.py
binomial_probability/Generaldistribution.py
binomial_probability/__init__.py
binomial_probability.egg-info/PKG-INFO
binomial_probability.egg-info/SOURCES.txt
binomial_probability.egg-info/dependency_links.txt
binomial_probability.egg-info/not-zip-safe
binomial_probability.egg-info/top_level.txt