Metadata-Version: 1.0
Name: binomial-probability
Version: 0.1
Summary: Gaussian distributions
Home-page: UNKNOWN
Author: Tolulope Adegunle
Author-email: toluadegunle@gmail.com
License: UNKNOWN
Platform: UNKNOWN
